example/fifo_story/rtl/bit_walk.sv
// Walk a captured word out one bit per clock, LSB first, for five cycles.
// Halfway through — after two good bits — the low byte is inverted.
`timescale 1ns/1ps

module bit_walk (
    input  logic        clk,
    input  logic        rst_n,
    input  logic        load,
    input  logic [31:0] data_in,
    output logic        bit_out,
    output logic        bit_expected,
    output logic        bit_valid,
    output logic [31:0] shift_reg,
    output logic        corrupt
);
    logic [31:0] golden;
    logic [2:0]  emitted;
    logic        active;
    logic        smashed;

    always_ff @(posedge clk) begin
        if (!rst_n) begin
            shift_reg    <= 32'd0;
            golden       <= 32'd0;
            emitted      <= 3'd0;
            active       <= 1'b0;
            smashed      <= 1'b0;
            bit_out      <= 1'b0;
            bit_expected <= 1'b0;
            bit_valid    <= 1'b0;
            corrupt      <= 1'b0;
        end else if (load) begin
            shift_reg    <= data_in;
            golden       <= data_in;
            emitted      <= 3'd0;
            active       <= 1'b1;
            smashed      <= 1'b0;
            bit_valid    <= 1'b0;
            corrupt      <= 1'b0;
        end else if (active && !smashed && emitted == 3'd2) begin
            // Two bits have already left intact. Smash the byte still inside.
            shift_reg[7:0] <= shift_reg[7:0] ^ 8'hFF;
            smashed        <= 1'b1;
            corrupt        <= 1'b1;
            bit_valid      <= 1'b0;
        end else if (active) begin
            bit_out      <= shift_reg[0];
            bit_expected <= golden[0];
            bit_valid    <= 1'b1;
            corrupt      <= 1'b0;
            shift_reg    <= {1'b0, shift_reg[31:1]};
            golden       <= {1'b0, golden[31:1]};
            emitted      <= emitted + 3'd1;
            if (emitted == 3'd4) active <= 1'b0;
        end else begin
            bit_valid <= 1'b0;
            corrupt   <= 1'b0;
        end
    end
endmodule

example/fifo_story/rtl/fifo16.sv
// 16-entry, 32-bit synchronous FIFO.
`timescale 1ns/1ps

module fifo16 (
    input  logic        clk,
    input  logic        rst_n,
    input  logic        push,
    input  logic [31:0] wdata,
    input  logic        pop,
    output logic [31:0] rdata,
    output logic        full,
    output logic        empty,
    output logic [4:0]  count
);
    logic [31:0] mem [0:15];
    logic [3:0]  wr_ptr;
    logic [3:0]  rd_ptr;
    logic [4:0]  count_q;

    wire do_push = push && !full;
    wire do_pop  = pop  && !empty;

    assign full  = (count_q == 5'd16);
    assign empty = (count_q == 5'd0);
    assign count = count_q;
    assign rdata = mem[rd_ptr];

    integer i;
    always_ff @(posedge clk) begin
        if (!rst_n) begin
            wr_ptr  <= 4'd0;
            rd_ptr  <= 4'd0;
            count_q <= 5'd0;
            for (i = 0; i < 16; i = i + 1) mem[i] <= 32'd0;
        end else begin
            if (do_push) begin
                mem[wr_ptr] <= wdata;
                wr_ptr <= wr_ptr + 4'd1;
            end
            if (do_pop) rd_ptr <= rd_ptr + 4'd1;
            case ({do_push, do_pop})
                2'b10: count_q <= count_q + 5'd1;
                2'b01: count_q <= count_q - 5'd1;
                default: ;
            endcase
        end
    end
endmodule

example/fifo_story/rtl/tb_fifo_story.sv
// Story: one random word enters a 16-deep FIFO, the FIFO fills while that
// word is still queued, the same word comes out intact, then a shifter walks
// it out one bit per cycle. Halfway through, the low byte is inverted.
`timescale 1ns/1ps

module tb_fifo_story;
    localparam logic [31:0] TRACKED = 32'hA5C319E7;

    logic        clk;
    logic        rst_n;
    logic        push;
    logic        pop;
    logic        load;
    logic [31:0] wdata;
    logic [31:0] rdata;
    logic        full;
    logic        empty;
    logic [4:0]  count;
    logic        bit_out;
    logic        bit_expected;
    logic        bit_valid;
    logic [31:0] shift_reg;
    logic        corrupt;

    fifo16 u_fifo (
        .clk   (clk),
        .rst_n (rst_n),
        .push  (push),
        .wdata (wdata),
        .pop   (pop),
        .rdata (rdata),
        .full  (full),
        .empty (empty),
        .count (count)
    );

    bit_walk u_shift (
        .clk          (clk),
        .rst_n        (rst_n),
        .load         (load),
        .data_in      (rdata),
        .bit_out      (bit_out),
        .bit_expected (bit_expected),
        .bit_valid    (bit_valid),
        .shift_reg    (shift_reg),
        .corrupt      (corrupt)
    );

    initial clk = 1'b0;
    always #5 clk = ~clk;

    logic [31:0] words [0:15];
    integer n;

    task automatic push_word(input logic [31:0] data);
        @(negedge clk);
        push  = 1'b1;
        pop   = 1'b0;
        load  = 1'b0;
        wdata = data;
        @(posedge clk);
    endtask

    task automatic pop_word(input logic capture);
        @(negedge clk);
        push = 1'b0;
        pop  = 1'b1;
        load = capture;
        @(posedge clk);
    endtask

    initial begin
        words[0]  = 32'h4B1D77A2;
        words[1]  = 32'hE03C19F5;
        words[2]  = 32'h18F06C2D;
        words[3]  = 32'h91AA004E;
        words[4]  = 32'h77E2B318;
        words[5]  = 32'h0D5FC6A1;
        words[6]  = 32'hB3402E99;
        words[7]  = 32'h55C18D07;
        words[8]  = TRACKED;
        words[9]  = 32'h6E214AF0;
        words[10] = 32'hC8B703D4;
        words[11] = 32'h13DE90AB;
        words[12] = 32'hF04A6621;
        words[13] = 32'h2B9CE154;
        words[14] = 32'h80F37C6E;
        words[15] = 32'hD17625B8;

        rst_n = 1'b0;
        push  = 1'b0;
        pop   = 1'b0;
        load  = 1'b0;
        wdata = 32'd0;

        repeat (3) @(posedge clk);
        @(negedge clk);
        rst_n = 1'b1;

        // Eight words, then the one we follow, then seven more until full.
        for (n = 0; n < 16; n = n + 1) push_word(words[n]);

        // Drain the eight words ahead of the tracked one.
        for (n = 0; n < 8; n = n + 1) pop_word(1'b0);

        // The tracked word is at the head. Pop it into the shifter.
        pop_word(1'b1);
        @(negedge clk);
        push = 1'b0;
        pop  = 1'b0;
        load = 1'b0;

        // Two good bits, the byte smash, then three damaged bits.
        repeat (8) @(posedge clk);
        $finish;
    end

    initial begin
        $dumpfile("waves.vcd");
        $dumpvars(0, tb_fifo_story);
    end
endmodule

example/fifo_story/sim/waves.vcd
$version Generated by VerilatedVcd $end
$timescale 1ps $end
 $scope module $rootio $end
 $upscope $end
 $scope module tb_fifo_story $end
  $var wire 32 \ TRACKED [31:0] $end
  $var wire 1 Y clk $end
  $var wire 1 # rst_n $end
  $var wire 1 $ push $end
  $var wire 1 % pop $end
  $var wire 1 & load $end
  $var wire 32 ' wdata [31:0] $end
  $var wire 32 9 rdata [31:0] $end
  $var wire 1 : full $end
  $var wire 1 ; empty $end
  $var wire 5 < count [4:0] $end
  $var wire 1 = bit_out $end
  $var wire 1 > bit_expected $end
  $var wire 1 ? bit_valid $end
  $var wire 32 @ shift_reg [31:0] $end
  $var wire 1 A corrupt $end
  $var wire 32 ( words[0] [31:0] $end
  $var wire 32 ) words[1] [31:0] $end
  $var wire 32 * words[2] [31:0] $end
  $var wire 32 + words[3] [31:0] $end
  $var wire 32 , words[4] [31:0] $end
  $var wire 32 - words[5] [31:0] $end
  $var wire 32 . words[6] [31:0] $end
  $var wire 32 / words[7] [31:0] $end
  $var wire 32 0 words[8] [31:0] $end
  $var wire 32 1 words[9] [31:0] $end
  $var wire 32 2 words[10] [31:0] $end
  $var wire 32 3 words[11] [31:0] $end
  $var wire 32 4 words[12] [31:0] $end
  $var wire 32 5 words[13] [31:0] $end
  $var wire 32 6 words[14] [31:0] $end
  $var wire 32 7 words[15] [31:0] $end
  $var wire 32 8 n [31:0] $end
  $scope module u_fifo $end
   $var wire 1 Y clk $end
   $var wire 1 # rst_n $end
   $var wire 1 $ push $end
   $var wire 32 ' wdata [31:0] $end
   $var wire 1 % pop $end
   $var wire 32 9 rdata [31:0] $end
   $var wire 1 : full $end
   $var wire 1 ; empty $end
   $var wire 5 < count [4:0] $end
   $var wire 32 B mem[0] [31:0] $end
   $var wire 32 C mem[1] [31:0] $end
   $var wire 32 D mem[2] [31:0] $end
   $var wire 32 E mem[3] [31:0] $end
   $var wire 32 F mem[4] [31:0] $end
   $var wire 32 G mem[5] [31:0] $end
   $var wire 32 H mem[6] [31:0] $end
   $var wire 32 I mem[7] [31:0] $end
   $var wire 32 J mem[8] [31:0] $end
   $var wire 32 K mem[9] [31:0] $end
   $var wire 32 L mem[10] [31:0] $end
   $var wire 32 M mem[11] [31:0] $end
   $var wire 32 N mem[12] [31:0] $end
   $var wire 32 O mem[13] [31:0] $end
   $var wire 32 P mem[14] [31:0] $end
   $var wire 32 Q mem[15] [31:0] $end
   $var wire 4 R wr_ptr [3:0] $end
   $var wire 4 S rd_ptr [3:0] $end
   $var wire 5 < count_q [4:0] $end
   $var wire 1 Z do_push $end
   $var wire 1 [ do_pop $end
   $var wire 32 T i [31:0] $end
  $upscope $end
  $scope module u_shift $end
   $var wire 1 Y clk $end
   $var wire 1 # rst_n $end
   $var wire 1 & load $end
   $var wire 32 9 data_in [31:0] $end
   $var wire 1 = bit_out $end
   $var wire 1 > bit_expected $end
   $var wire 1 ? bit_valid $end
   $var wire 32 @ shift_reg [31:0] $end
   $var wire 1 A corrupt $end
   $var wire 32 U golden [31:0] $end
   $var wire 3 V emitted [2:0] $end
   $var wire 1 W active $end
   $var wire 1 X smashed $end
  $upscope $end
 $upscope $end
$enddefinitions $end


#0
0#
0$
0%
0&
b00000000000000000000000000000000 '
b01001011000111010111011110100010 (
b11100000001111000001100111110101 )
b00011000111100000110110000101101 *
b10010001101010100000000001001110 +
b01110111111000101011001100011000 ,
b00001101010111111100011010100001 -
b10110011010000000010111010011001 .
b01010101110000011000110100000111 /
b10100101110000110001100111100111 0
b01101110001000010100101011110000 1
b11001000101101110000001111010100 2
b00010011110111101001000010101011 3
b11110000010010100110011000100001 4
b00101011100111001110000101010100 5
b10000000111100110111110001101110 6
b11010001011101100010010110111000 7
b00000000000000000000000000000000 8
b00000000000000000000000000000000 9
0:
1;
b00000 <
0=
0>
0?
b00000000000000000000000000000000 @
0A
b00000000000000000000000000000000 B
b00000000000000000000000000000000 C
b00000000000000000000000000000000 D
b00000000000000000000000000000000 E
b00000000000000000000000000000000 F
b00000000000000000000000000000000 G
b00000000000000000000000000000000 H
b00000000000000000000000000000000 I
b00000000000000000000000000000000 J
b00000000000000000000000000000000 K
b00000000000000000000000000000000 L
b00000000000000000000000000000000 M
b00000000000000000000000000000000 N
b00000000000000000000000000000000 O
b00000000000000000000000000000000 P
b00000000000000000000000000000000 Q
b0000 R
b0000 S
b00000000000000000000000000000000 T
b00000000000000000000000000000000 U
b000 V
0W
0X
0Y
0Z
0[
b10100101110000110001100111100111 \
#5000
b00000000000000000000000000010000 T
1Y
#10000
0Y
#15000
1Y
#20000
0Y
#25000
1Y
#30000
1#
0Y
#35000
1Y
#40000
1$
b01001011000111010111011110100010 '
0Y
1Z
#45000
b00000000000000000000000000000001 8
b01001011000111010111011110100010 9
0;
b00001 <
b01001011000111010111011110100010 B
b0001 R
1Y
#50000
b11100000001111000001100111110101 '
0Y
#55000
b00000000000000000000000000000010 8
b00010 <
b11100000001111000001100111110101 C
b0010 R
1Y
#60000
b00011000111100000110110000101101 '
0Y
#65000
b00000000000000000000000000000011 8
b00011 <
b00011000111100000110110000101101 D
b0011 R
1Y
#70000
b10010001101010100000000001001110 '
0Y
#75000
b00000000000000000000000000000100 8
b00100 <
b10010001101010100000000001001110 E
b0100 R
1Y
#80000
b01110111111000101011001100011000 '
0Y
#85000
b00000000000000000000000000000101 8
b00101 <
b01110111111000101011001100011000 F
b0101 R
1Y
#90000
b00001101010111111100011010100001 '
0Y
#95000
b00000000000000000000000000000110 8
b00110 <
b00001101010111111100011010100001 G
b0110 R
1Y
#100000
b10110011010000000010111010011001 '
0Y
#105000
b00000000000000000000000000000111 8
b00111 <
b10110011010000000010111010011001 H
b0111 R
1Y
#110000
b01010101110000011000110100000111 '
0Y
#115000
b00000000000000000000000000001000 8
b01000 <
b01010101110000011000110100000111 I
b1000 R
1Y
#120000
b10100101110000110001100111100111 '
0Y
#125000
b00000000000000000000000000001001 8
b01001 <
b10100101110000110001100111100111 J
b1001 R
1Y
#130000
b01101110001000010100101011110000 '
0Y
#135000
b00000000000000000000000000001010 8
b01010 <
b01101110001000010100101011110000 K
b1010 R
1Y
#140000
b11001000101101110000001111010100 '
0Y
#145000
b00000000000000000000000000001011 8
b01011 <
b11001000101101110000001111010100 L
b1011 R
1Y
#150000
b00010011110111101001000010101011 '
0Y
#155000
b00000000000000000000000000001100 8
b01100 <
b00010011110111101001000010101011 M
b1100 R
1Y
#160000
b11110000010010100110011000100001 '
0Y
#165000
b00000000000000000000000000001101 8
b01101 <
b11110000010010100110011000100001 N
b1101 R
1Y
#170000
b00101011100111001110000101010100 '
0Y
#175000
b00000000000000000000000000001110 8
b01110 <
b00101011100111001110000101010100 O
b1110 R
1Y
#180000
b10000000111100110111110001101110 '
0Y
#185000
b00000000000000000000000000001111 8
b01111 <
b10000000111100110111110001101110 P
b1111 R
1Y
#190000
b11010001011101100010010110111000 '
0Y
#195000
b00000000000000000000000000010000 8
1:
b10000 <
b11010001011101100010010110111000 Q
b0000 R
1Y
0Z
#200000
0$
1%
0Y
1[
#205000
b00000000000000000000000000000001 8
b11100000001111000001100111110101 9
0:
b01111 <
b0001 S
1Y
#210000
0Y
#215000
b00000000000000000000000000000010 8
b00011000111100000110110000101101 9
b01110 <
b0010 S
1Y
#220000
0Y
#225000
b00000000000000000000000000000011 8
b10010001101010100000000001001110 9
b01101 <
b0011 S
1Y
#230000
0Y
#235000
b00000000000000000000000000000100 8
b01110111111000101011001100011000 9
b01100 <
b0100 S
1Y
#240000
0Y
#245000
b00000000000000000000000000000101 8
b00001101010111111100011010100001 9
b01011 <
b0101 S
1Y
#250000
0Y
#255000
b00000000000000000000000000000110 8
b10110011010000000010111010011001 9
b01010 <
b0110 S
1Y
#260000
0Y
#265000
b00000000000000000000000000000111 8
b01010101110000011000110100000111 9
b01001 <
b0111 S
1Y
#270000
0Y
#275000
b00000000000000000000000000001000 8
b10100101110000110001100111100111 9
b01000 <
b1000 S
1Y
#280000
1&
0Y
#285000
b01101110001000010100101011110000 9
b00111 <
b10100101110000110001100111100111 @
b1001 S
b10100101110000110001100111100111 U
1W
1Y
#290000
0%
0&
0Y
0[
#295000
1=
1>
1?
b01010010111000011000110011110011 @
b01010010111000011000110011110011 U
b001 V
1Y
#300000
0Y
#305000
b00101001011100001100011001111001 @
b00101001011100001100011001111001 U
b010 V
1Y
#310000
0Y
#315000
0?
b00101001011100001100011010000110 @
1A
1X
1Y
#320000
0Y
#325000
0=
1?
b00010100101110000110001101000011 @
0A
b00010100101110000110001100111100 U
b011 V
1Y
#330000
0Y
#335000
1=
0>
b00001010010111000011000110100001 @
b00001010010111000011000110011110 U
b100 V
1Y
#340000
0Y
#345000
b00000101001011100001100011010000 @
b00000101001011100001100011001111 U
b101 V
0W
1Y
#350000
0Y
#355000
0?
1Y
